{
  "timestamp": "2025-07-28 15:54:02",
  "total_signals": 15,
  "active_signals": 6,
  "signals": [
    {
      "Timestamp": "2025-07-28 16:11:02",
      "Symbol": "USDJPY",
      "Signal": "BUY",
      "Entry_Price": 149.15152,
      "Stop_Loss": 148.85448,
      "Take_Profit": 149.63758,
      "Lot_Size": 0.04,
      "Confidence": 0.66,
      "Risk_Reward": 1.64,
      "Magic_Number": 123450,
      "Timeframe": "H1",
      "Status": "Pending",
      "Comment": "GenX_BUY_USDJPY"
    },
    {
      "Timestamp": "2025-07-28 15:36:02",
      "Symbol": "AUDUSD",
      "Signal": "BUY",
      "Entry_Price": 0.65824,
      "Stop_Loss": 0.65451,
      "Take_Profit": 0.663,
      "Lot_Size": 0.05,
      "Confidence": 0.7,
      "Risk_Reward": 1.28,
      "Magic_Number": 123451,
      "Timeframe": "H4",
      "Status": "Pending",
      "Comment": "GenX_BUY_AUDUSD"
    },
    {
      "Timestamp": "2025-07-28 16:07:02",
      "Symbol": "USDCAD",
      "Signal": "SELL",
      "Entry_Price": 1.36142,
      "Stop_Loss": 1.36361,
      "Take_Profit": 1.35477,
      "Lot_Size": 0.05,
      "Confidence": 0.68,
      "Risk_Reward": 3.04,
      "Magic_Number": 123452,
      "Timeframe": "H4",
      "Status": "Active",
      "Comment": "GenX_SELL_USDCAD"
    },
    {
      "Timestamp": "2025-07-28 16:08:02",
      "Symbol": "EURUSD",
      "Signal": "SELL",
      "Entry_Price": 1.10913,
      "Stop_Loss": 1.11182,
      "Take_Profit": 1.10191,
      "Lot_Size": 0.02,
      "Confidence": 0.67,
      "Risk_Reward": 2.69,
      "Magic_Number": 123453,
      "Timeframe": "H1",
      "Status": "Active",
      "Comment": "GenX_SELL_EURUSD"
    },
    {
      "Timestamp": "2025-07-28 15:41:02",
      "Symbol": "USDCHF",
      "Signal": "BUY",
      "Entry_Price": 0.88216,
      "Stop_Loss": 0.87862,
      "Take_Profit": 0.88956,
      "Lot_Size": 0.1,
      "Confidence": 0.93,
      "Risk_Reward": 2.09,
      "Magic_Number": 123454,
      "Timeframe": "M15",
      "Status": "Filled",
      "Comment": "GenX_BUY_USDCHF"
    },
    {
      "Timestamp": "2025-07-28 15:48:02",
      "Symbol": "AUDUSD",
      "Signal": "BUY",
      "Entry_Price": 0.66142,
      "Stop_Loss": 0.6588,
      "Take_Profit": 0.6708,
      "Lot_Size": 0.02,
      "Confidence": 0.73,
      "Risk_Reward": 3.59,
      "Magic_Number": 123455,
      "Timeframe": "D1",
      "Status": "Filled",
      "Comment": "GenX_BUY_AUDUSD"
    },
    {
      "Timestamp": "2025-07-28 15:49:02",
      "Symbol": "NZDUSD",
      "Signal": "BUY",
      "Entry_Price": 0.58967,
      "Stop_Loss": 0.58475,
      "Take_Profit": 0.59932,
      "Lot_Size": 0.07,
      "Confidence": 0.72,
      "Risk_Reward": 1.96,
      "Magic_Number": 123456,
      "Timeframe": "M15",
      "Status": "Filled",
      "Comment": "GenX_BUY_NZDUSD"
    },
    {
      "Timestamp": "2025-07-28 15:58:02",
      "Symbol": "USDCAD",
      "Signal": "BUY",
      "Entry_Price": 1.36916,
      "Stop_Loss": 1.36714,
      "Take_Profit": 1.37323,
      "Lot_Size": 0.06,
      "Confidence": 0.85,
      "Risk_Reward": 2.01,
      "Magic_Number": 123457,
      "Timeframe": "D1",
      "Status": "Active",
      "Comment": "GenX_BUY_USDCAD"
    },
    {
      "Timestamp": "2025-07-28 15:55:02",
      "Symbol": "USDCAD",
      "Signal": "SELL",
      "Entry_Price": 1.37114,
      "Stop_Loss": 1.37502,
      "Take_Profit": 1.36515,
      "Lot_Size": 0.08,
      "Confidence": 0.76,
      "Risk_Reward": 1.55,
      "Magic_Number": 123458,
      "Timeframe": "D1",
      "Status": "Filled",
      "Comment": "GenX_SELL_USDCAD"
    },
    {
      "Timestamp": "2025-07-28 16:10:02",
      "Symbol": "USDCAD",
      "Signal": "SELL",
      "Entry_Price": 1.36175,
      "Stop_Loss": 1.36467,
      "Take_Profit": 1.35417,
      "Lot_Size": 0.04,
      "Confidence": 0.78,
      "Risk_Reward": 2.6,
      "Magic_Number": 123459,
      "Timeframe": "H1",
      "Status": "Active",
      "Comment": "GenX_SELL_USDCAD"
    },
    {
      "Timestamp": "2025-07-28 15:48:02",
      "Symbol": "NZDUSD",
      "Signal": "SELL",
      "Entry_Price": 0.58925,
      "Stop_Loss": 0.59187,
      "Take_Profit": 0.58331,
      "Lot_Size": 0.08,
      "Confidence": 0.68,
      "Risk_Reward": 2.27,
      "Magic_Number": 123460,
      "Timeframe": "D1",
      "Status": "Filled",
      "Comment": "GenX_SELL_NZDUSD"
    },
    {
      "Timestamp": "2025-07-28 15:49:02",
      "Symbol": "USDCAD",
      "Signal": "SELL",
      "Entry_Price": 1.35915,
      "Stop_Loss": 1.36335,
      "Take_Profit": 1.35353,
      "Lot_Size": 0.08,
      "Confidence": 0.81,
      "Risk_Reward": 1.33,
      "Magic_Number": 123461,
      "Timeframe": "H1",
      "Status": "Active",
      "Comment": "GenX_SELL_USDCAD"
    },
    {
      "Timestamp": "2025-07-28 15:37:02",
      "Symbol": "GBPUSD",
      "Signal": "SELL",
      "Entry_Price": 1.27336,
      "Stop_Loss": 1.27657,
      "Take_Profit": 1.26711,
      "Lot_Size": 0.07,
      "Confidence": 0.93,
      "Risk_Reward": 1.94,
      "Magic_Number": 123462,
      "Timeframe": "H4",
      "Status": "Filled",
      "Comment": "GenX_SELL_GBPUSD"
    },
    {
      "Timestamp": "2025-07-28 15:54:02",
      "Symbol": "GBPUSD",
      "Signal": "SELL",
      "Entry_Price": 1.26777,
      "Stop_Loss": 1.27091,
      "Take_Profit": 1.25891,
      "Lot_Size": 0.08,
      "Confidence": 0.67,
      "Risk_Reward": 2.82,
      "Magic_Number": 123463,
      "Timeframe": "H1",
      "Status": "Active",
      "Comment": "GenX_SELL_GBPUSD"
    },
    {
      "Timestamp": "2025-07-28 15:44:02",
      "Symbol": "AUDUSD",
      "Signal": "SELL",
      "Entry_Price": 0.6593,
      "Stop_Loss": 0.66258,
      "Take_Profit": 0.65508,
      "Lot_Size": 0.01,
      "Confidence": 0.78,
      "Risk_Reward": 1.29,
      "Magic_Number": 123464,
      "Timeframe": "D1",
      "Status": "Pending",
      "Comment": "GenX_SELL_AUDUSD"
    }
  ]
}